odoo/addons/mail_composer_cc_bcc/README.rst
odoo/addons/mail_composer_cc_bcc/__init__.py
odoo/addons/mail_composer_cc_bcc/__manifest__.py
odoo/addons/mail_composer_cc_bcc/i18n/de.po
odoo/addons/mail_composer_cc_bcc/i18n/es.po
odoo/addons/mail_composer_cc_bcc/i18n/it.po
odoo/addons/mail_composer_cc_bcc/i18n/mail_composer_cc_bcc.pot
odoo/addons/mail_composer_cc_bcc/models/__init__.py
odoo/addons/mail_composer_cc_bcc/models/ir_mail_server.py
odoo/addons/mail_composer_cc_bcc/models/mail_mail.py
odoo/addons/mail_composer_cc_bcc/models/mail_message.py
odoo/addons/mail_composer_cc_bcc/models/mail_template.py
odoo/addons/mail_composer_cc_bcc/models/mail_thread.py
odoo/addons/mail_composer_cc_bcc/models/res_company.py
odoo/addons/mail_composer_cc_bcc/readme/CONFIGURE.md
odoo/addons/mail_composer_cc_bcc/readme/CONTRIBUTORS.md
odoo/addons/mail_composer_cc_bcc/readme/CREDITS.md
odoo/addons/mail_composer_cc_bcc/readme/DESCRIPTION.md
odoo/addons/mail_composer_cc_bcc/readme/USAGE.md
odoo/addons/mail_composer_cc_bcc/static/description/icon.png
odoo/addons/mail_composer_cc_bcc/static/description/index.html
odoo/addons/mail_composer_cc_bcc/static/img/email_template_form_cc_bcc.png
odoo/addons/mail_composer_cc_bcc/static/img/mail_compose_message_default_cc_bcc.png
odoo/addons/mail_composer_cc_bcc/static/img/mail_compose_message_template_cc_bcc.png
odoo/addons/mail_composer_cc_bcc/static/img/res_company_form_default_cc_bcc.png
odoo/addons/mail_composer_cc_bcc/tests/__init__.py
odoo/addons/mail_composer_cc_bcc/tests/test_mail_cc_bcc.py
odoo/addons/mail_composer_cc_bcc/views/mail_mail_views.xml
odoo/addons/mail_composer_cc_bcc/views/mail_message_views.xml
odoo/addons/mail_composer_cc_bcc/views/mail_template_views.xml
odoo/addons/mail_composer_cc_bcc/views/res_company_views.xml
odoo/addons/mail_composer_cc_bcc/wizards/__init__.py
odoo/addons/mail_composer_cc_bcc/wizards/mail_compose_message.py
odoo/addons/mail_composer_cc_bcc/wizards/mail_compose_message_view.xml
odoo_addon_mail_composer_cc_bcc-18.0.1.0.2.3.dist-info/METADATA
odoo_addon_mail_composer_cc_bcc-18.0.1.0.2.3.dist-info/WHEEL
odoo_addon_mail_composer_cc_bcc-18.0.1.0.2.3.dist-info/top_level.txt
odoo_addon_mail_composer_cc_bcc-18.0.1.0.2.3.dist-info/RECORD
