Metadata-Version: 2.1
Name: odoo-addon-mail_composer_cc_bcc
Version: 18.0.1.0.2.3
Requires-Python: >=3.10
Requires-Dist: odoo==18.0.*
Summary: This module enables sending mail to CC and BCC partners in mail composer form.
Home-page: https://github.com/OCA/mail
License: AGPL-3
Author: Camptocamp, Odoo Community Association (OCA)
Author-email: support@odoo-community.org
Classifier: Programming Language :: Python
Classifier: Framework :: Odoo
Classifier: Framework :: Odoo :: 18.0
Classifier: License :: OSI Approved :: GNU Affero General Public License v3
Classifier: Development Status :: 3 - Alpha
